aliyunsdkservicemesh/__init__.py
aliyunsdkservicemesh/endpoint.py
aliyunsdkservicemesh/request/__init__.py
aliyunsdkservicemesh/request/v20200111/AddClusterIntoServiceMeshRequest.py
aliyunsdkservicemesh/request/v20200111/AddVmAppToMeshRequest.py
aliyunsdkservicemesh/request/v20200111/CreateServiceMeshRequest.py
aliyunsdkservicemesh/request/v20200111/DeleteServiceMeshRequest.py
aliyunsdkservicemesh/request/v20200111/DescribeCensRequest.py
aliyunsdkservicemesh/request/v20200111/DescribeClusterGrafanaRequest.py
aliyunsdkservicemesh/request/v20200111/DescribeClusterPrometheusRequest.py
aliyunsdkservicemesh/request/v20200111/DescribeClustersInServiceMeshRequest.py
aliyunsdkservicemesh/request/v20200111/DescribeGuestClusterAccessLogDashboardsRequest.py
aliyunsdkservicemesh/request/v20200111/DescribeIngressGatewaysRequest.py
aliyunsdkservicemesh/request/v20200111/DescribeServiceMeshDetailRequest.py
aliyunsdkservicemesh/request/v20200111/DescribeServiceMeshKubeconfigRequest.py
aliyunsdkservicemesh/request/v20200111/DescribeServiceMeshesRequest.py
aliyunsdkservicemesh/request/v20200111/DescribeUpgradeVersionRequest.py
aliyunsdkservicemesh/request/v20200111/GetDiagnosisRequest.py
aliyunsdkservicemesh/request/v20200111/GetRegisteredServiceEndpointsRequest.py
aliyunsdkservicemesh/request/v20200111/GetRegisteredServiceNamespacesRequest.py
aliyunsdkservicemesh/request/v20200111/GetRegisteredServicesRequest.py
aliyunsdkservicemesh/request/v20200111/GetServiceMeshSlbRequest.py
aliyunsdkservicemesh/request/v20200111/GetVmAppMeshInfoRequest.py
aliyunsdkservicemesh/request/v20200111/GetVmMetaRequest.py
aliyunsdkservicemesh/request/v20200111/RemoveClusterFromServiceMeshRequest.py
aliyunsdkservicemesh/request/v20200111/RemoveVmAppFromMeshRequest.py
aliyunsdkservicemesh/request/v20200111/RunDiagnosisRequest.py
aliyunsdkservicemesh/request/v20200111/UpdateIstioInjectionConfigRequest.py
aliyunsdkservicemesh/request/v20200111/UpdateMeshFeatureRequest.py
aliyun_python_sdk_servicemesh-1.0.5.dist-info/LICENSE
aliyun_python_sdk_servicemesh-1.0.5.dist-info/METADATA
aliyun_python_sdk_servicemesh-1.0.5.dist-info/WHEEL
aliyun_python_sdk_servicemesh-1.0.5.dist-info/top_level.txt
aliyun_python_sdk_servicemesh-1.0.5.dist-info/RECORD
